geoipdb_loader/__init__.py
geoipdb_loader/apps.py
geoipdb_loader/models.py
geoipdb_loader/tasks.py
geoipdb_loader/management/__init__.py
geoipdb_loader/management/commands/__init__.py
geoipdb_loader/management/commands/download_geoipdb.py
django_geoipdb_loader-1.0.0.dist-info/LICENSE
django_geoipdb_loader-1.0.0.dist-info/METADATA
django_geoipdb_loader-1.0.0.dist-info/WHEEL
django_geoipdb_loader-1.0.0.dist-info/top_level.txt
django_geoipdb_loader-1.0.0.dist-info/RECORD
