Metadata-Version: 2.1
Name: django-geoipdb-loader
Version: 1.0.0
Summary: Helps download and keep updated maxmind's geoip db required for django GeoIP
Home-page: https://github.com/kalekseev/django-geoipdb-loader
Author: Konstantin Alekseev
Author-email: kv.alekseev@gmail.com
License: UNKNOWN
Keywords: django,geoip
Platform: UNKNOWN
Classifier: Development Status :: 4 - Beta
Classifier: Environment :: Web Environment
Classifier: Framework :: Django
Classifier: Intended Audience :: Developers
Classifier: License :: OSI Approved :: BSD License
Classifier: Operating System :: OS Independent
Classifier: Programming Language :: Python
Classifier: Programming Language :: Python :: 3
Classifier: Programming Language :: Python :: 3.6
Classifier: Programming Language :: Python :: 3.7
Classifier: Programming Language :: Python :: 3.8
